timebomb/__init__.py
timebomb/app.py
timebomb/cli.py
timebomb/client.py
timebomb/models.py
timebomb/forms/__init__.py
timebomb/forms/cut.py
timebomb/forms/end.py
timebomb/forms/game.py
timebomb/forms/login.py
timebomb/forms/notif.py
timebomb/forms/utils.py
timebomb/forms/wait.py
timebomb_client-0.4.0.dist-info/LICENSE
timebomb_client-0.4.0.dist-info/METADATA
timebomb_client-0.4.0.dist-info/WHEEL
timebomb_client-0.4.0.dist-info/entry_points.txt
timebomb_client-0.4.0.dist-info/top_level.txt
timebomb_client-0.4.0.dist-info/RECORD
