Metadata-Version: 2.1
Name: timebomb-client
Version: 0.4.0
Summary: Time Bomb from your terminal.
Home-page: https://github.com/thmslmr/timebomb-client
Author: Thomas Le Meur
Author-email: thmslmr@gmail.com
License: MIT
Platform: UNKNOWN
Classifier: License :: OSI Approved :: MIT License
Classifier: Natural Language :: English
Classifier: Programming Language :: Python
Classifier: Programming Language :: Python :: 3
Classifier: Programming Language :: Python :: 3 :: Only
Classifier: Programming Language :: Python :: 3.6
Classifier: Programming Language :: Python :: 3.7
Classifier: Topic :: Games/Entertainment
Classifier: Environment :: Console
Classifier: Intended Audience :: End Users/Desktop
Requires-Python: >=3.6
Requires-Dist: npyscreen
Requires-Dist: python-socketio[client]
